struct_writer/__init__.py
struct_writer/default_template_c.py
struct_writer/default_template_rust.py
struct_writer/definitions.py
struct_writer/generate_structured_code.py
struct_writer/render_c.py
struct_writer/render_rust.py
struct_writer/struct_parse/__init__.py
struct_writer/struct_parse/struct_parse.py
struct_writer/templating/__init__.py
struct_writer-0.8.2.dist-info/METADATA
struct_writer-0.8.2.dist-info/WHEEL
struct_writer-0.8.2.dist-info/entry_points.txt
struct_writer-0.8.2.dist-info/licenses/LICENSE
struct_writer-0.8.2.dist-info/RECORD
