Metadata-Version: 2.4
Name: struct_writer
Version: 0.8.2
Summary: Generate structured code for APIs and documentation
Project-URL: repository, https://github.com/drbartling/struct-writer
Author-email: Ryan Bartling <ryan.bartling@gmail.com>
License-File: LICENSE
Requires-Python: <3.15,>=3.12
Requires-Dist: click>=8.3.1
Requires-Dist: pydantic>=2.12.5
Requires-Dist: pyyaml>=6.0.3
Requires-Dist: rich>=14.2.0
